{"files_javascript_class.md":"ARUbsDkx","files_others_jsdoc.md":"IRWtYIHj","files_others_webpack.md":"T9A6rxmH","files_css_grid.md":"u273JRbJ","files_javascript_timecount.md":"_mfys-dE","files_others_websocket.md":"fwTESMwC","files_vue_repaintreflow.md":"W-biz_te","files_vue_render.md":"MlYMs3OF","methods_common_saveasjson.md":"kIIGkTlQ","files_vue_slot.md":"vRB_ikxh","files_javascript_eventloop.md":"APaClQaL","files_element_datepicker.md":"E1hmj7TJ","methods_common_uuid.md":"MWRYN5DF","files_typescript_basictype.md":"XQEy3DbS","files_microfront_introduce.md":"OgSOUyaG","methods_common_concurrencyrequest.md":"YLZ2pS8k","files_javascript_prototype.md":"3Tn5nCWt","about_team.md":"kX-30G1D","methods_object_deepclone.md":"TnV5mf04","files_index.md":"_SohPWHj","files_vue_scoped.md":"pKOX35-p","files_css_textflow.md":"i-FAU-X6","files_javascript_clone.md":"aKnHjlsl","files_javascript_deconstruct.md":"4jNhagg7","files_javascript_debouncethrottling.md":"giQ6-01D","methods_common_blobdownload.md":"RaJTHOWA","methods_object_isempty.md":"5jxXn_fM","methods_common_waterfall.md":"zx2Mn2L3","methods_array_deduplication.md":"jit1RrNS","files_javascript_asyncprogram.md":"4GAuaGFB","files_dayjs_commoncommand.md":"zU5CeYMR","about_index.md":"NkCfuMJa","files_typescript_introduce.md":"IK5dvEDs","files_vue_statepersistence.md":"awxYAA9a","files_javascript_datatype.md":"TdReLZAM","files_others_gitcreate.md":"Se_D8VN5","files_designpattern_singletonpattern.md":"wnRMKeWl","files_typescript_interface.md":"8UuikB-l","files_css_bem.md":"z2Fdk1z9","files_javascript_context.md":"KsHAU0qj","methods_tree_treefilter.md":"RzACtYdP","files_git_instruction.md":"LWnaokr5","files_javascript_closure.md":"1ov_gfHc","methods_common_canvassignature.md":"6CHnRpiT","files_designpattern_observepattern.md":"OXVe1Tep","files_designpattern_strategypattern.md":"n_ZWCfq7","files_javascript_recursion.md":"0eShE40k","methods_array_getintersection.md":"TTKy8_5v","methods_array_gettruth.md":"3DMW8o6f","methods_array_hasintersection.md":"cs3ok3Gp","methods_index.md":"55RKr67i","files_webgis_index.md":"NowWPI_B","methods_object_hasvaluesin.md":"Lgr32SMV","methods_common_operate.md":"3RyOhdPl","files_javascript_regexp.md":"PMlvaWlW","methods_object_getdatafromobject.md":"9h4imRPI","methods_common_timecount.md":"xpRBTOqV","files_javascript_treetraversal.md":"mOSyR1o-","files_git_introduction.md":"_2Yt0Eya","files_hexo_hexocommand.md":"g0MISzmb","files_designpattern_index.md":"nVK-IrOg","files_javascript_new.md":"8sMiaPUC","files_vuesource_index.md":"0JTXhQ22","index.md":"LrN2dA0V","files_designpattern_factorypattern.md":"f6pHxGcV","files_javascript_applybindcall.md":"Isxshbqb","methods_tree_treetraverse.md":"tOOFf_fe","files_javascript_this.md":"jJ7OBurb"}
